build/lib/build/lib/dataoutsider/__init__.py
build/lib/build/lib/dataoutsider/__main__.py
build/lib/build/lib/dataoutsider/bubble_series.py
build/lib/build/lib/dataoutsider/multi_chord.py
build/lib/build/lib/dataoutsider/pie_tree.py
build/lib/build/lib/dataoutsider/data/aircraft_2020.csv
build/lib/build/lib/dataoutsider/data/athlete_events.csv
build/lib/dataoutsider/__init__.py
build/lib/dataoutsider/__main__.py
build/lib/dataoutsider/bubble_series.py
build/lib/dataoutsider/multi_chord.py
build/lib/dataoutsider/pie_tree.py
build/lib/dataoutsider/data/aircraft_2020.csv
build/lib/dataoutsider/data/athlete_events.csv
dataoutsider/__init__.py
dataoutsider/__main__.py
dataoutsider/bubble_series.py
dataoutsider/multi_chord.py
dataoutsider/pie_tree.py
dataoutsider/data/aircraft_2020.csv
dataoutsider/data/athlete_events.csv
dataoutsider-1.2.3.dist-info/LICENSE-COM
dataoutsider-1.2.3.dist-info/LICENSE-NC
dataoutsider-1.2.3.dist-info/METADATA
dataoutsider-1.2.3.dist-info/WHEEL
dataoutsider-1.2.3.dist-info/top_level.txt
dataoutsider-1.2.3.dist-info/RECORD
