Metadata-Version: 2.1
Name: dataoutsider
Version: 1.2.3
Summary: Data visualization toolbox.
Home-page: https://pypi.org/project/dataoutsider/
Author: Nick Gerend
Author-email: nickgerend@gmail.com
License: Dual License: Non-Commercial Use License and Commercial Use License, see LICENSE-NC and LICENSE-COM for terms
Classifier: Programming Language :: Python :: 3.7
License-File: LICENSE-COM
License-File: LICENSE-NC
Requires-Dist: pandas
Requires-Dist: numpy
Requires-Dist: matplotlib
